rknfind/__init__.py
rknfind/__main__.py
rknfind/util.py
rknfind/app/__init__.py
rknfind/app/i18n.py
rknfind/app/cli/__init__.py
rknfind/app/cli/args.py
rknfind/db/__init__.py
rknfind/db/model.py
rknfind/rkn/__init__.py
rknfind/rkn/csv.py
rknfind/rkn/dump.py
rknfind-2.1.0a1.data/data/rknfind/i18n/ru_RU/LC_MESSAGES/rknfind.mo
rknfind-2.1.0a1.dist-info/METADATA
rknfind-2.1.0a1.dist-info/WHEEL
rknfind-2.1.0a1.dist-info/entry_points.txt
rknfind-2.1.0a1.dist-info/top_level.txt
rknfind-2.1.0a1.dist-info/RECORD
