Metadata-Version: 2.1
Name: rknfind
Version: 2.1.0a1
Summary: Dig into RKN dump with ease
Home-page: https://github.com/scpketer/rknfind
Author: scpketer
Author-email: scpketer@protonmail.ch
License: UNKNOWN
Keywords: rkn roskomnadzor cli find
Platform: UNKNOWN
Requires-Python: >=3, <4
Requires-Dist: argcomplete
Requires-Dist: appdirs
Requires-Dist: requests
Provides-Extra: db
Requires-Dist: peewee ; extra == 'db'
Provides-Extra: git
Requires-Dist: gitpython ; extra == 'git'
